stockeventreport/__init__.py
stockeventreport/core.py
stockeventreport/static/Dashboard.js
stockeventreport/static/Dashboard.js.map
stockeventreport/static/Panel.js
stockeventreport/static/Panel.js.map
stockeventreport/static/Settings.js
stockeventreport/static/Settings.js.map
stockeventreport/static/.vite/manifest.json
stockeventreport/static/assets/Plugins-yOmUdOt6.js
stockeventreport/static/assets/Plugins-yOmUdOt6.js.map
stockeventreport-0.1.0.dist-info/licenses/LICENSE
stockeventreport-0.1.0.dist-info/METADATA
stockeventreport-0.1.0.dist-info/WHEEL
stockeventreport-0.1.0.dist-info/entry_points.txt
stockeventreport-0.1.0.dist-info/top_level.txt
stockeventreport-0.1.0.dist-info/RECORD
